dissect/volume/__init__.py
dissect/volume/exceptions.py
dissect/volume/ldm.py
dissect/volume/vss.py
dissect/volume/ddf/__init__.py
dissect/volume/ddf/c_ddf.py
dissect/volume/ddf/ddf.py
dissect/volume/disk/__init__.py
dissect/volume/disk/disk.py
dissect/volume/disk/partition.py
dissect/volume/disk/schemes/__init__.py
dissect/volume/disk/schemes/apm.py
dissect/volume/disk/schemes/bsd.py
dissect/volume/disk/schemes/gpt.py
dissect/volume/disk/schemes/mbr.py
dissect/volume/dm/__init__.py
dissect/volume/dm/btree.py
dissect/volume/dm/c_dm.py
dissect/volume/dm/thin.py
dissect/volume/lvm/__init__.py
dissect/volume/lvm/c_lvm2.py
dissect/volume/lvm/lvm2.py
dissect/volume/lvm/metadata.py
dissect/volume/lvm/physical.py
dissect/volume/md/__init__.py
dissect/volume/md/c_md.py
dissect/volume/md/md.py
dissect/volume/raid/__init__.py
dissect/volume/raid/raid.py
dissect/volume/raid/stream.py
dissect/volume/vinum/__init__.py
dissect/volume/vinum/c_vinum.py
dissect/volume/vinum/config.py
dissect/volume/vinum/vinum.py
dissect_volume-3.16.dist-info/licenses/COPYRIGHT
dissect_volume-3.16.dist-info/licenses/LICENSE
dissect_volume-3.16.dist-info/METADATA
dissect_volume-3.16.dist-info/WHEEL
dissect_volume-3.16.dist-info/top_level.txt
dissect_volume-3.16.dist-info/RECORD
